MANIFEST.in
README.rst
setup.py
async_messages/__init__.py
async_messages/messages.py
async_messages/middleware.py
django_async_messages.egg-info/PKG-INFO
django_async_messages.egg-info/SOURCES.txt
django_async_messages.egg-info/dependency_links.txt
django_async_messages.egg-info/requires.txt
django_async_messages.egg-info/top_level.txt