Metadata-Version: 1.0
Name: django-async-messages
Version: 0.3
Summary: Send asynchronous messages to users (eg from offline scripts).  Useful for integration with Celery
Home-page: https://github.com/codeinthehole/django-async-messages
Author: David Winterbottom
Author-email: david.winterbottom@gmail.com
License: UNKNOWN
Platform: UNKNOWN
